midsummer/__init__.py
midsummer/midsummer.py
midsummer-0.1.5.dist-info/licenses/LICENSE.md
midsummer-0.1.5.dist-info/METADATA
midsummer-0.1.5.dist-info/WHEEL
midsummer-0.1.5.dist-info/top_level.txt
midsummer-0.1.5.dist-info/RECORD
