Metadata-Version: 2.4
Name: midsummer
Version: 0.1.5
Summary: Return date for midsummer
Requires-Python: >=3.12
License-File: LICENSE.md
Dynamic: license-file
